twitter.common.collections-0.3.10-py2.7-nspkg.pth
twitter/common/collections/__init__.py
twitter/common/collections/ordereddict.py
twitter/common/collections/orderedset.py
twitter/common/collections/ringbuffer.py
twitter.common.collections-0.3.10.dist-info/DESCRIPTION.rst
twitter.common.collections-0.3.10.dist-info/METADATA
twitter.common.collections-0.3.10.dist-info/RECORD
twitter.common.collections-0.3.10.dist-info/WHEEL
twitter.common.collections-0.3.10.dist-info/metadata.json
twitter.common.collections-0.3.10.dist-info/namespace_packages.txt
twitter.common.collections-0.3.10.dist-info/top_level.txt
twitter.common.collections-0.3.10.dist-info/zip-safe
